src/__init__.py
src/app/__init__.py
src/app/auth.py
src/app/msg.py
src/tests/__init__.py
src/tests/test_auth.py
src/tests/test_msg.py
webforum_api-0.1.0.dist-info/LICENSE
webforum_api-0.1.0.dist-info/METADATA
webforum_api-0.1.0.dist-info/WHEEL
webforum_api-0.1.0.dist-info/top_level.txt
webforum_api-0.1.0.dist-info/RECORD
