Metadata-Version: 2.1
Name: webforum-api
Version: 0.1.0
Summary: Useful towel-related stuff.
Home-page: http://pypi.python.org/pypi/webforum_api/
Author: Clement Onawole
Author-email: dapo.onawole@gmail.com
License: LICENSE
Keywords: networking eventlet nonblocking internet
Platform: UNKNOWN
Classifier: License :: OSI Approved :: GNU General Public License (GPL)
Classifier: Programming Language :: Python
Classifier: Development Status :: 4 - Beta
Classifier: Intended Audience :: Developers
Classifier: Topic :: Internet
Requires-Dist: fastapi
Requires-Dist: uvicorn
Requires-Dist: pymongo
Requires-Dist: pytest
